snowpenguin/__init__.py
snowpenguin/django/__init__.py
snowpenguin/django/recaptcha3/__init__.py
snowpenguin/django/recaptcha3/fields.py
snowpenguin/django/recaptcha3/tests.py
snowpenguin/django/recaptcha3/widgets.py
snowpenguin/django/recaptcha3/locale/it/LC_MESSAGES/django.mo
snowpenguin/django/recaptcha3/migrations/__init__.py
snowpenguin/django/recaptcha3/templates/snowpenguin/recaptcha/recaptcha_execute.html
snowpenguin/django/recaptcha3/templates/snowpenguin/recaptcha/recaptcha_hidden_input.html
snowpenguin/django/recaptcha3/templates/snowpenguin/recaptcha/recaptcha_init.html
snowpenguin/django/recaptcha3/templates/snowpenguin/recaptcha/recaptcha_ready.html
snowpenguin/django/recaptcha3/templatetags/__init__.py
snowpenguin/django/recaptcha3/templatetags/recaptcha3.py
django_recaptcha3-0.4.0.dist-info/LICENSE
django_recaptcha3-0.4.0.dist-info/METADATA
django_recaptcha3-0.4.0.dist-info/WHEEL
django_recaptcha3-0.4.0.dist-info/top_level.txt
django_recaptcha3-0.4.0.dist-info/RECORD
